README.md
setup.py
nacos/__init__.py
nacos/base.py
nacos/client.py
nacos/instance.py
nacos/namespace.py
nacos/operator.py
nacos/service.py
nacos_client_python.egg-info/PKG-INFO
nacos_client_python.egg-info/SOURCES.txt
nacos_client_python.egg-info/dependency_links.txt
nacos_client_python.egg-info/top_level.txt