Metadata-Version: 2.1
Name: nacos-client-python
Version: 0.0.1
Summary: nacos python client tool.
Home-page: https://gitee.com/hubert22/nacos_client_python
Author: Hubert Shelley
Author-email: hubertshelley@163.com
License: MIT
Platform: UNKNOWN
Classifier: License :: OSI Approved :: Apache Software License
Classifier: Programming Language :: Python
Classifier: Programming Language :: Python :: 3
Classifier: Programming Language :: Python :: 3.6
Classifier: Programming Language :: Python :: Implementation :: CPython
Classifier: Programming Language :: Python :: Implementation :: PyPy
Requires-Python: >=3.6.0
